flarespy/__init__.py
flarespy/data/flarespy.mplstyle
flarespy/data/model.dat
flarespy/data/params.npy
flarespy/flarespy.py
flarespy/simulate.py
flarespy/train.py
flarespy/utils.py
flarespy/version.py
flarespy-0.15.0.dist-info/LICENSE
flarespy-0.15.0.dist-info/METADATA
flarespy-0.15.0.dist-info/WHEEL
flarespy-0.15.0.dist-info/RECORD
